Metadata-Version: 2.1
Name: ia-planner-jerson-gpt
Version: 0.1
Summary: Planificador de tareas con IA implementando diferentes modelos - 2024
Home-page: https://pypi.org/project/ia-planner-jerson/
Author: Jerson Danilo Florez Parra
Author-email: jerchiton.97@gmail.com
Requires-Dist: aiohappyeyeballs==2.4.3
Requires-Dist: aiohttp==3.10.10
Requires-Dist: aiosignal==1.3.1
Requires-Dist: annotated-types==0.7.0
Requires-Dist: anyio==4.6.2.post1
Requires-Dist: asgiref==3.8.1
Requires-Dist: attrs==24.2.0
Requires-Dist: backoff==2.2.1
Requires-Dist: bcrypt==4.2.0
Requires-Dist: build==1.2.2.post1
Requires-Dist: cachetools==5.5.0
Requires-Dist: certifi==2024.8.30
Requires-Dist: charset-normalizer==3.4.0
Requires-Dist: chroma-hnswlib==0.7.6
Requires-Dist: chromadb==0.5.18
Requires-Dist: click==8.1.7
Requires-Dist: cohere==5.11.3
Requires-Dist: colorama==0.4.6
Requires-Dist: coloredlogs==15.0.1
Requires-Dist: dataclasses-json==0.6.7
Requires-Dist: Deprecated==1.2.14
Requires-Dist: diskcache==5.6.3
Requires-Dist: distro==1.9.0
Requires-Dist: durationpy==0.9
Requires-Dist: fastapi==0.115.4
Requires-Dist: fastavro==1.9.7
Requires-Dist: filelock==3.16.1
Requires-Dist: flatbuffers==24.3.25
Requires-Dist: frozenlist==1.5.0
Requires-Dist: fsspec==2024.10.0
Requires-Dist: google-auth==2.35.0
Requires-Dist: googleapis-common-protos==1.65.0
Requires-Dist: greenlet==3.1.1
Requires-Dist: grpcio==1.67.1
Requires-Dist: h11==0.14.0
Requires-Dist: httpcore==1.0.6
Requires-Dist: httptools==0.6.4
Requires-Dist: httpx==0.27.2
Requires-Dist: httpx-sse==0.4.0
Requires-Dist: huggingface-hub==0.26.2
Requires-Dist: humanfriendly==10.0
Requires-Dist: idna==3.10
Requires-Dist: importlib_metadata==8.5.0
Requires-Dist: importlib_resources==6.4.5
Requires-Dist: jiter==0.7.0
Requires-Dist: jsonpatch==1.33
Requires-Dist: jsonpointer==3.0.0
Requires-Dist: kubernetes==31.0.0
Requires-Dist: langchain==0.3.7
Requires-Dist: langchain-chroma==0.1.4
Requires-Dist: langchain-community==0.3.5
Requires-Dist: langchain-core==0.3.19
Requires-Dist: langchain-openai==0.2.9
Requires-Dist: langchain-text-splitters==0.3.2
Requires-Dist: langsmith==0.1.140
Requires-Dist: llmx==0.0.21a0
Requires-Dist: markdown-it-py==3.0.0
Requires-Dist: marshmallow==3.23.1
Requires-Dist: mdurl==0.1.2
Requires-Dist: mmh3==5.0.1
Requires-Dist: monotonic==1.6
Requires-Dist: mpmath==1.3.0
Requires-Dist: multidict==6.1.0
Requires-Dist: mypy-extensions==1.0.0
Requires-Dist: numpy==1.26.4
Requires-Dist: oauthlib==3.2.2
Requires-Dist: onnxruntime==1.20.0
Requires-Dist: openai==1.54.1
Requires-Dist: opentelemetry-api==1.28.0
Requires-Dist: opentelemetry-exporter-otlp-proto-common==1.28.0
Requires-Dist: opentelemetry-exporter-otlp-proto-grpc==1.28.0
Requires-Dist: opentelemetry-instrumentation==0.49b0
Requires-Dist: opentelemetry-instrumentation-asgi==0.49b0
Requires-Dist: opentelemetry-instrumentation-fastapi==0.49b0
Requires-Dist: opentelemetry-proto==1.28.0
Requires-Dist: opentelemetry-sdk==1.28.0
Requires-Dist: opentelemetry-semantic-conventions==0.49b0
Requires-Dist: opentelemetry-util-http==0.49b0
Requires-Dist: orjson==3.10.11
Requires-Dist: overrides==7.7.0
Requires-Dist: packaging==24.1
Requires-Dist: parameterized==0.9.0
Requires-Dist: posthog==3.7.0
Requires-Dist: propcache==0.2.0
Requires-Dist: protobuf==5.28.3
Requires-Dist: pyasn1==0.6.1
Requires-Dist: pyasn1_modules==0.4.1
Requires-Dist: pydantic==2.9.2
Requires-Dist: pydantic-settings==2.6.1
Requires-Dist: pydantic_core==2.23.4
Requires-Dist: Pygments==2.18.0
Requires-Dist: pypdf==5.1.0
Requires-Dist: PyPika==0.48.9
Requires-Dist: pyproject_hooks==1.2.0
Requires-Dist: pyreadline3==3.5.4
Requires-Dist: python-dateutil==2.9.0.post0
Requires-Dist: python-dotenv==1.0.1
Requires-Dist: PyYAML==6.0.2
Requires-Dist: regex==2024.9.11
Requires-Dist: requests==2.32.3
Requires-Dist: requests-oauthlib==2.0.0
Requires-Dist: requests-toolbelt==1.0.0
Requires-Dist: rich==13.9.4
Requires-Dist: rsa==4.9
Requires-Dist: setuptools==75.6.0
Requires-Dist: shellingham==1.5.4
Requires-Dist: six==1.16.0
Requires-Dist: sniffio==1.3.1
Requires-Dist: SQLAlchemy==2.0.35
Requires-Dist: starlette==0.41.2
Requires-Dist: sympy==1.13.3
Requires-Dist: tenacity==9.0.0
Requires-Dist: tiktoken==0.8.0
Requires-Dist: tokenizers==0.20.3
Requires-Dist: tqdm==4.66.6
Requires-Dist: typer==0.12.5
Requires-Dist: types-requests==2.32.0.20241016
Requires-Dist: typing-inspect==0.9.0
Requires-Dist: typing_extensions==4.12.2
Requires-Dist: urllib3==2.2.3
Requires-Dist: uvicorn==0.32.0
Requires-Dist: watchfiles==0.24.0
Requires-Dist: websocket-client==1.8.0
Requires-Dist: websockets==13.1
Requires-Dist: wrapt==1.16.0
Requires-Dist: yarl==1.17.1
Requires-Dist: zipp==3.20.2
